ipython_reload.py
ipython_reload-0.0.1.dist-info/LICENSE
ipython_reload-0.0.1.dist-info/METADATA
ipython_reload-0.0.1.dist-info/WHEEL
ipython_reload-0.0.1.dist-info/top_level.txt
ipython_reload-0.0.1.dist-info/RECORD
