Metadata-Version: 2.1
Name: ipython-reload
Version: 0.0.1
Summary: IPython magic command to reload modules on demand
Home-page: https://github.com/sivel/ipython-reload
Author: Matt Martz
Author-email: matt@sivel.net
License: UNKNOWN
Project-URL: Bug Reports, https://github.com/sivel/ipython-reload/issues
Project-URL: Source, https://github.com/sivel/ipython-reload/
Keywords: ipython magic
Platform: UNKNOWN
Classifier: Development Status :: 3 - Alpha
Classifier: Intended Audience :: Developers
Classifier: License :: OSI Approved :: MIT License
Classifier: Programming Language :: Python :: 3
Classifier: Programming Language :: Python :: 3.6
Classifier: Programming Language :: Python :: 3.7
Classifier: Programming Language :: Python :: 3.8
Requires-Python: >=3.5, <4
